<ns0:re3data xmlns:ns0="http://www.re3data.org/schema/2-2" xmlns:xsi="http://www.w3.org/2001/XMLSchema-instance" xsi:schemaLocation="http://www.re3data.org/schema/2-2 http://schema.re3data.org/2-2/re3dataV2-2.xsd">
    <ns0:repository>
        <ns0:re3data.orgIdentifier>r3d100010941</ns0:re3data.orgIdentifier>
        <ns0:repositoryName language="eng">National Archive of Criminal Justice Data, Terrorism and Preparedness Data Resource Center</ns0:repositoryName>
                    <ns0:additionalName language="eng">NACJD, TPDRC</ns0:additionalName>
                <ns0:repositoryURL>http://www.icpsr.umich.edu/icpsrweb/content/NACJD/guides/tpdrc.html</ns0:repositoryURL>
                <ns0:description language="eng">The Terrorism and Preparedness Data Resource Center (TPDRC) archives and distributes data collected by government agencies, non-governmental organizations (NGOs), and researchers about the nature of intra- (domestic) and international terrorism incidents, organizations, perpetrators, and victims; governmental and nongovernmental responses to terror, including primary, secondary, and tertiary interventions; and citizen's attitudes towards terrorism, terror incidents, and the response to terror. The Terrorism and Preparedness Survey Archive (TaPSA) is part of the Terrorism &amp; Preparedness Data Resource Center (TPDRC).</ns0:description>
                    <ns0:repositoryContact>tpdrc@start.umd.edu</ns0:repositoryContact>
                            <ns0:type>disciplinary</ns0:type>
                <ns0:size updated="2019-01-15">2.850 studies; 72 series;</ns0:size>
        <ns0:startDate>2007</ns0:startDate>
        <ns0:endDate />
                    <ns0:repositoryLanguage>eng</ns0:repositoryLanguage>
                            <ns0:subject subjectScheme="DFG">1 Humanities and Social Sciences</ns0:subject>
                    <ns0:subject subjectScheme="DFG">113 Jurisprudence</ns0:subject>
                    <ns0:subject subjectScheme="DFG">11305 Criminology</ns0:subject>
                    <ns0:subject subjectScheme="DFG">12 Social and Behavioural Sciences</ns0:subject>
                <ns0:missionStatementURL>http://www.icpsr.umich.edu/icpsrweb/content/NACJD/mission.html</ns0:missionStatementURL>
                    <ns0:contentType contentTypeScheme="parse">Scientific and statistical data formats</ns0:contentType>
                    <ns0:contentType contentTypeScheme="parse">Standard office documents</ns0:contentType>
                    <ns0:contentType contentTypeScheme="parse">Structured text</ns0:contentType>
                            <ns0:providerType>dataProvider</ns0:providerType>
                    <ns0:providerType>serviceProvider</ns0:providerType>
                            <ns0:keyword>national security</ns0:keyword>
                    <ns0:keyword>surveys</ns0:keyword>
                    <ns0:keyword>terrorism</ns0:keyword>
                            <ns0:institution>
                <ns0:institutionName language="eng">Michigan State University, School of Criminal Justice</ns0:institutionName>
                                <ns0:institutionCountry>USA</ns0:institutionCountry>
                                    <ns0:responsibilityType>general</ns0:responsibilityType>
                                <ns0:institutionType>non-profit</ns0:institutionType>
                <ns0:institutionURL>https://cj.msu.edu/</ns0:institutionURL>
                                <ns0:responsibilityStartDate />
                <ns0:responsibilityEndDate />
                                    <ns0:institutionContact>https://cj.msu.edu/contact-us/</ns0:institutionContact>
                            </ns0:institution>
                    <ns0:institution>
                <ns0:institutionName language="eng">National Archive of Criminal Justice Data</ns0:institutionName>
                                    <ns0:institutionAdditionalName language="eng">NACJD</ns0:institutionAdditionalName>
                                <ns0:institutionCountry>USA</ns0:institutionCountry>
                                    <ns0:responsibilityType>general</ns0:responsibilityType>
                                <ns0:institutionType>non-profit</ns0:institutionType>
                <ns0:institutionURL>https://www.icpsr.umich.edu/icpsrweb/content/NACJD/index.html</ns0:institutionURL>
                                <ns0:responsibilityStartDate />
                <ns0:responsibilityEndDate />
                            </ns0:institution>
                    <ns0:institution>
                <ns0:institutionName language="eng">National Institute of Justice</ns0:institutionName>
                                    <ns0:institutionAdditionalName language="eng">NIJ</ns0:institutionAdditionalName>
                                <ns0:institutionCountry>USA</ns0:institutionCountry>
                                    <ns0:responsibilityType>funding</ns0:responsibilityType>
                                <ns0:institutionType>non-profit</ns0:institutionType>
                <ns0:institutionURL>https://www.nij.gov/Pages/welcome.aspx</ns0:institutionURL>
                                <ns0:responsibilityStartDate />
                <ns0:responsibilityEndDate />
                            </ns0:institution>
                    <ns0:institution>
                <ns0:institutionName language="eng">National Science Foundation</ns0:institutionName>
                                    <ns0:institutionAdditionalName language="eng">NSF</ns0:institutionAdditionalName>
                                <ns0:institutionCountry>USA</ns0:institutionCountry>
                                    <ns0:responsibilityType>funding</ns0:responsibilityType>
                                <ns0:institutionType>non-profit</ns0:institutionType>
                <ns0:institutionURL>https://nsf.gov/</ns0:institutionURL>
                                    <ns0:institutionIdentifier>RRID:SCR_012938</ns0:institutionIdentifier>
                                    <ns0:institutionIdentifier>RRID:nlx_inv_1005118</ns0:institutionIdentifier>
                                <ns0:responsibilityStartDate />
                <ns0:responsibilityEndDate />
                            </ns0:institution>
                    <ns0:institution>
                <ns0:institutionName language="eng">U.S. Department of Homeland Security</ns0:institutionName>
                                <ns0:institutionCountry>USA</ns0:institutionCountry>
                                    <ns0:responsibilityType>funding</ns0:responsibilityType>
                                <ns0:institutionType>non-profit</ns0:institutionType>
                <ns0:institutionURL>https://www.dhs.gov/</ns0:institutionURL>
                                <ns0:responsibilityStartDate />
                <ns0:responsibilityEndDate />
                            </ns0:institution>
                    <ns0:institution>
                <ns0:institutionName language="eng">University of Maryland, National Consortium for the Study of Terrorism and Responses to Terrorism</ns0:institutionName>
                                    <ns0:institutionAdditionalName language="eng">START</ns0:institutionAdditionalName>
                                <ns0:institutionCountry>USA</ns0:institutionCountry>
                                    <ns0:responsibilityType>general</ns0:responsibilityType>
                                <ns0:institutionType>non-profit</ns0:institutionType>
                <ns0:institutionURL>https://www.start.umd.edu/</ns0:institutionURL>
                                <ns0:responsibilityStartDate />
                <ns0:responsibilityEndDate />
                                    <ns0:institutionContact>tpdrc@start.umd.edu</ns0:institutionContact>
                            </ns0:institution>
                    <ns0:institution>
                <ns0:institutionName language="eng">University of Michigan,  Institute for Social Research,  Inter-university Consortium for Political and Social Research</ns0:institutionName>
                                    <ns0:institutionAdditionalName language="eng">ICPSR</ns0:institutionAdditionalName>
                                <ns0:institutionCountry>USA</ns0:institutionCountry>
                                    <ns0:responsibilityType>general</ns0:responsibilityType>
                                    <ns0:responsibilityType>technical</ns0:responsibilityType>
                                <ns0:institutionType>non-profit</ns0:institutionType>
                <ns0:institutionURL>http://www.icpsr.umich.edu/icpsrweb/index.jsp</ns0:institutionURL>
                                    <ns0:institutionIdentifier>RRID:SCR_003194</ns0:institutionIdentifier>
                                    <ns0:institutionIdentifier>RRID:nif-0000-00615</ns0:institutionIdentifier>
                                <ns0:responsibilityStartDate />
                <ns0:responsibilityEndDate />
                                    <ns0:institutionContact>nacjd@icpsr.umich.edu</ns0:institutionContact>
                            </ns0:institution>
                            <ns0:policy>
                <ns0:policyName>ICPSR Access Policy Framework</ns0:policyName>
                <ns0:policyURL>https://www.icpsr.umich.edu/icpsrweb/content/datamanagement/preservation/policies/access-policy-framework.html</ns0:policyURL>
            </ns0:policy>
                <ns0:databaseAccess>
            <ns0:databaseAccessType>open</ns0:databaseAccessType>
                    </ns0:databaseAccess>
                            <ns0:dataAccess>
                <ns0:dataAccessType>closed</ns0:dataAccessType>
                            </ns0:dataAccess>
                    <ns0:dataAccess>
                <ns0:dataAccessType>open</ns0:dataAccessType>
                            </ns0:dataAccess>
                    <ns0:dataAccess>
                <ns0:dataAccessType>restricted</ns0:dataAccessType>
                                    <ns0:dataAccessRestriction>feeRequired</ns0:dataAccessRestriction>
                                    <ns0:dataAccessRestriction>institutional membership</ns0:dataAccessRestriction>
                                    <ns0:dataAccessRestriction>other</ns0:dataAccessRestriction>
                                    <ns0:dataAccessRestriction>registration</ns0:dataAccessRestriction>
                            </ns0:dataAccess>
                            <ns0:dataLicense>
                <ns0:dataLicenseName>other</ns0:dataLicenseName>
                <ns0:dataLicenseURL>https://www.icpsr.umich.edu/files/NACJD/pdf/ProtectingConfidentialDataattheNationalArchiveofCriminalJusticeData(v2.2016).pdf</ns0:dataLicenseURL>
            </ns0:dataLicense>
                    <ns0:dataLicense>
                <ns0:dataLicenseName>other</ns0:dataLicenseName>
                <ns0:dataLicenseURL>https://www.icpsr.umich.edu/icpsrweb/content/ICPSR/access/restricted/index.html</ns0:dataLicenseURL>
            </ns0:dataLicense>
                            <ns0:dataUpload>
                <ns0:dataUploadType>restricted</ns0:dataUploadType>
                                    <ns0:dataUploadRestriction>registration</ns0:dataUploadRestriction>
                            </ns0:dataUpload>
                            <ns0:dataUploadLicense>
                <ns0:dataUploadLicenseName>Deposit data</ns0:dataUploadLicenseName>
                <ns0:dataUploadLicenseURL>https://www.icpsr.umich.edu/icpsrweb/content/NACJD/archiving/index.html</ns0:dataUploadLicenseURL>
            </ns0:dataUploadLicense>
                            <ns0:software>
                <ns0:softwareName>unknown</ns0:softwareName>
            </ns0:software>
                <ns0:versioning>yes</ns0:versioning>
                            <ns0:pidSystem>DOI</ns0:pidSystem>
                <ns0:citationGuidelineURL>https://www.icpsr.umich.edu/icpsrweb/content/shared/NACJD/faqs/why-and-how-should-i-cite-data.html</ns0:citationGuidelineURL>
                <ns0:enhancedPublication>yes</ns0:enhancedPublication>
        <ns0:qualityManagement>yes</ns0:qualityManagement>
                            <ns0:metadataStandard>
                <ns0:metadataStandardName metadataStandardScheme="DCC">DDI - Data Documentation Initiative</ns0:metadataStandardName>
                <ns0:metadataStandardURL>http://www.dcc.ac.uk/resources/metadata-standards/ddi-data-documentation-initiative</ns0:metadataStandardURL>
            </ns0:metadataStandard>
                        <ns0:remarks>TPDRC uses DDI metadata Standard. If you locate a membership-only study that fits your research needs and would like to purchase it, you can find more information about this process on the Nonmember Access to Data page.</ns0:remarks>
        <ns0:entryDate>2014-08-25</ns0:entryDate>
        <ns0:lastUpdate>2019-01-15</ns0:lastUpdate>
    </ns0:repository>
</ns0:re3data>