<ns0:re3data xmlns:ns0="http://www.re3data.org/schema/2-2" xmlns:xsi="http://www.w3.org/2001/XMLSchema-instance" xsi:schemaLocation="http://www.re3data.org/schema/2-2 http://schema.re3data.org/2-2/re3dataV2-2.xsd">
    <ns0:repository>
        <ns0:re3data.orgIdentifier>r3d100011254</ns0:re3data.orgIdentifier>
        <ns0:repositoryName language="eng">CfA Dataverses</ns0:repositoryName>
                    <ns0:additionalName language="eng">The Astronomy Dataverse Network</ns0:additionalName>
                <ns0:repositoryURL>https://dataverse.harvard.edu/dataverse/cfa</ns0:repositoryURL>
                <ns0:description language="eng">The Astronomy data repository at Harvard is currently open to all scientific data from astronomical institutions worldwide. Incorporating Astroinformatics of galaxies and quasars Dataverse. The Astronomy Dataverse is connected to the indexing services provided by the SAO/NASA Astrophysical Data Service (ADS).</ns0:description>
                    <ns0:repositoryContact>https://dataverse.harvard.edu/dataverse/cfa#</ns0:repositoryContact>
                            <ns0:type>disciplinary</ns0:type>
                <ns0:size updated="2021-04-16">38 dataverses; 125 datasets; 2.035 files</ns0:size>
        <ns0:startDate />
        <ns0:endDate />
                    <ns0:repositoryLanguage>eng</ns0:repositoryLanguage>
                            <ns0:subject subjectScheme="DFG">3 Natural Sciences</ns0:subject>
                    <ns0:subject subjectScheme="DFG">311 Astrophysics and Astronomy</ns0:subject>
                    <ns0:subject subjectScheme="DFG">32 Physics</ns0:subject>
                <ns0:missionStatementURL />
                    <ns0:contentType contentTypeScheme="parse">Databases</ns0:contentType>
                    <ns0:contentType contentTypeScheme="parse">Standard office documents</ns0:contentType>
                            <ns0:providerType>dataProvider</ns0:providerType>
                            <ns0:keyword>physical sciences</ns0:keyword>
                            <ns0:institution>
                <ns0:institutionName language="eng">Dataverse Project</ns0:institutionName>
                                <ns0:institutionCountry>AAA</ns0:institutionCountry>
                                    <ns0:responsibilityType>technical</ns0:responsibilityType>
                                <ns0:institutionType>non-profit</ns0:institutionType>
                <ns0:institutionURL>https://dataverse.org/</ns0:institutionURL>
                                <ns0:responsibilityStartDate />
                <ns0:responsibilityEndDate />
                                    <ns0:institutionContact>https://dataverse.org/contact</ns0:institutionContact>
                                    <ns0:institutionContact>support@dataverse.org</ns0:institutionContact>
                            </ns0:institution>
                    <ns0:institution>
                <ns0:institutionName language="eng">Harvard Dataverse</ns0:institutionName>
                                <ns0:institutionCountry>USA</ns0:institutionCountry>
                                    <ns0:responsibilityType>technical</ns0:responsibilityType>
                                <ns0:institutionType>non-profit</ns0:institutionType>
                <ns0:institutionURL>https://dataverse.harvard.edu/</ns0:institutionURL>
                                <ns0:responsibilityStartDate />
                <ns0:responsibilityEndDate />
                            </ns0:institution>
                    <ns0:institution>
                <ns0:institutionName language="eng">Harvard Library</ns0:institutionName>
                                    <ns0:institutionAdditionalName language="eng">HL</ns0:institutionAdditionalName>
                                <ns0:institutionCountry>USA</ns0:institutionCountry>
                                    <ns0:responsibilityType>general</ns0:responsibilityType>
                                <ns0:institutionType>non-profit</ns0:institutionType>
                <ns0:institutionURL>https://library.harvard.edu/</ns0:institutionURL>
                                <ns0:responsibilityStartDate />
                <ns0:responsibilityEndDate />
                            </ns0:institution>
                    <ns0:institution>
                <ns0:institutionName language="eng">Harvard-Smithsonian Center for Astrophysics</ns0:institutionName>
                                    <ns0:institutionAdditionalName language="eng">cfA</ns0:institutionAdditionalName>
                                <ns0:institutionCountry>USA</ns0:institutionCountry>
                                    <ns0:responsibilityType>general</ns0:responsibilityType>
                                <ns0:institutionType>non-profit</ns0:institutionType>
                <ns0:institutionURL>https://www.cfa.harvard.edu/</ns0:institutionURL>
                                    <ns0:institutionIdentifier>ROR:03c3r2d17</ns0:institutionIdentifier>
                                <ns0:responsibilityStartDate />
                <ns0:responsibilityEndDate />
                                    <ns0:institutionContact>https://www.cfa.harvard.edu/about/contact</ns0:institutionContact>
                            </ns0:institution>
                    <ns0:institution>
                <ns0:institutionName language="eng">Institute for Quantitative Social Science</ns0:institutionName>
                                    <ns0:institutionAdditionalName language="eng">IQSS</ns0:institutionAdditionalName>
                                <ns0:institutionCountry>USA</ns0:institutionCountry>
                                    <ns0:responsibilityType>general</ns0:responsibilityType>
                                <ns0:institutionType>non-profit</ns0:institutionType>
                <ns0:institutionURL>https://www.iq.harvard.edu/</ns0:institutionURL>
                                <ns0:responsibilityStartDate />
                <ns0:responsibilityEndDate />
                            </ns0:institution>
                            <ns0:policy>
                <ns0:policyName>Dataverse Guides</ns0:policyName>
                <ns0:policyURL>http://guides.dataverse.org/en/latest/</ns0:policyURL>
            </ns0:policy>
                    <ns0:policy>
                <ns0:policyName>Dataverse Policies</ns0:policyName>
                <ns0:policyURL>https://dataverse.org/best-practices/harvard-dataverse-policies</ns0:policyURL>
            </ns0:policy>
                    <ns0:policy>
                <ns0:policyName>Harvard Dataverse General Terms of Use</ns0:policyName>
                <ns0:policyURL>https://dataverse.org/best-practices/harvard-dataverse-general-terms-use</ns0:policyURL>
            </ns0:policy>
                <ns0:databaseAccess>
            <ns0:databaseAccessType>open</ns0:databaseAccessType>
                    </ns0:databaseAccess>
                    <ns0:databaseLicense>
                <ns0:databaseLicenseName>Apache License 2.0</ns0:databaseLicenseName>
                <ns0:databaseLicenseURL>http://www.apache.org/licenses/LICENSE-2.0</ns0:databaseLicenseURL>
            </ns0:databaseLicense>
                            <ns0:dataAccess>
                <ns0:dataAccessType>open</ns0:dataAccessType>
                            </ns0:dataAccess>
                            <ns0:dataLicense>
                <ns0:dataLicenseName>CC0</ns0:dataLicenseName>
                <ns0:dataLicenseURL>https://creativecommons.org/share-your-work/public-domain/cc0/</ns0:dataLicenseURL>
            </ns0:dataLicense>
                    <ns0:dataLicense>
                <ns0:dataLicenseName>other</ns0:dataLicenseName>
                <ns0:dataLicenseURL>https://dataverse.org/best-practices/harvard-dataverse-general-terms-use</ns0:dataLicenseURL>
            </ns0:dataLicense>
                            <ns0:dataUpload>
                <ns0:dataUploadType>restricted</ns0:dataUploadType>
                                    <ns0:dataUploadRestriction>registration</ns0:dataUploadRestriction>
                            </ns0:dataUpload>
                                    <ns0:software>
                <ns0:softwareName>DataVerse</ns0:softwareName>
            </ns0:software>
                <ns0:versioning>yes</ns0:versioning>
                    <ns0:api apiType="REST">https://guides.dataverse.org/en/latest/api/native-api.html</ns0:api>
                    <ns0:api apiType="SWORD">https://guides.dataverse.org/en/latest/api/sword.html</ns0:api>
                    <ns0:api apiType="other">https://guides.dataverse.org/en/latest/api/dataaccess.html</ns0:api>
                    <ns0:api apiType="other">https://guides.dataverse.org/en/latest/api/search.html</ns0:api>
                    <ns0:api apiType="other">https://guides.dataverse.org/en/latest/api/index.html</ns0:api>
                            <ns0:pidSystem>DOI</ns0:pidSystem>
                    <ns0:pidSystem>hdl</ns0:pidSystem>
                <ns0:citationGuidelineURL>https://dataverse.org/best-practices/data-citation</ns0:citationGuidelineURL>
                <ns0:enhancedPublication>yes</ns0:enhancedPublication>
        <ns0:qualityManagement>yes</ns0:qualityManagement>
                            <ns0:metadataStandard>
                <ns0:metadataStandardName metadataStandardScheme="DCC">DDI - Data Documentation Initiative</ns0:metadataStandardName>
                <ns0:metadataStandardURL>http://www.dcc.ac.uk/resources/metadata-standards/ddi-data-documentation-initiative</ns0:metadataStandardURL>
            </ns0:metadataStandard>
                        <ns0:remarks>cfA dataverses is covered by Thomson Reuters Data Citation Index. Astroinformatics of galaxies and quasars Dataverse and theastrodata is covered by Thomson Reuters Data Citation Index.</ns0:remarks>
        <ns0:entryDate>2014-11-05</ns0:entryDate>
        <ns0:lastUpdate>2021-04-16</ns0:lastUpdate>
    </ns0:repository>
</ns0:re3data>