<ns0:re3data xmlns:ns0="http://www.re3data.org/schema/2-2" xmlns:xsi="http://www.w3.org/2001/XMLSchema-instance" xsi:schemaLocation="http://www.re3data.org/schema/2-2 http://schema.re3data.org/2-2/re3dataV2-2.xsd">
    <ns0:repository>
        <ns0:re3data.orgIdentifier>r3d100013617</ns0:re3data.orgIdentifier>
        <ns0:repositoryName language="eng">New Zealand's Biological Heritage National Science Challenge Data Repository</ns0:repositoryName>
                    <ns0:additionalName language="eng">NZ BioHeritage National Science Challenge Data Repository</ns0:additionalName>
                <ns0:repositoryURL>https://data.bioheritage.nz/</ns0:repositoryURL>
                <ns0:description language="eng">Data catalogue and repository for New Zealand's Biological Heritage National Science Challenge</ns0:description>
                    <ns0:repositoryContact>support@bioheritage.nz</ns0:repositoryContact>
                            <ns0:type>disciplinary</ns0:type>
                <ns0:size updated="2021-07-28">31 datasets; 5 collections; 2 groups</ns0:size>
        <ns0:startDate />
        <ns0:endDate />
                    <ns0:repositoryLanguage>eng</ns0:repositoryLanguage>
                            <ns0:subject subjectScheme="DFG">1 Humanities and Social Sciences</ns0:subject>
                    <ns0:subject subjectScheme="DFG">1 Humanities and Social Sciences</ns0:subject>
                    <ns0:subject subjectScheme="DFG">2 Life Sciences</ns0:subject>
                    <ns0:subject subjectScheme="DFG">207 Agriculture, Forestry, Horticulture and Veterinary Medicine</ns0:subject>
                    <ns0:subject subjectScheme="DFG">21 Biology</ns0:subject>
                    <ns0:subject subjectScheme="DFG">23 Agriculture, Forestry, Horticulture and Veterinary Medicine</ns0:subject>
                    <ns0:subject subjectScheme="DFG">3 Natural Sciences</ns0:subject>
                    <ns0:subject subjectScheme="DFG">34 Geosciences (including Geography)</ns0:subject>
                <ns0:missionStatementURL>https://data.bioheritage.nz/about</ns0:missionStatementURL>
                    <ns0:contentType contentTypeScheme="parse">Images</ns0:contentType>
                    <ns0:contentType contentTypeScheme="parse">Raw data</ns0:contentType>
                    <ns0:contentType contentTypeScheme="parse">Scientific and statistical data formats</ns0:contentType>
                    <ns0:contentType contentTypeScheme="parse">Source code</ns0:contentType>
                    <ns0:contentType contentTypeScheme="parse">Standard office documents</ns0:contentType>
                            <ns0:providerType>dataProvider</ns0:providerType>
                            <ns0:keyword>biosecurity</ns0:keyword>
                    <ns0:keyword>eDNA</ns0:keyword>
                    <ns0:keyword>gene</ns0:keyword>
                    <ns0:keyword>genetics</ns0:keyword>
                    <ns0:keyword>invasive species</ns0:keyword>
                    <ns0:keyword>mitochondrial DNA</ns0:keyword>
                    <ns0:keyword>pest control</ns0:keyword>
                    <ns0:keyword>synthetic biology</ns0:keyword>
                            <ns0:institution>
                <ns0:institutionName language="eng">Landcare Research NZ</ns0:institutionName>
                                    <ns0:institutionAdditionalName language="mri">Manaaki Whenua</ns0:institutionAdditionalName>
                                <ns0:institutionCountry>NZL</ns0:institutionCountry>
                                    <ns0:responsibilityType>general</ns0:responsibilityType>
                                    <ns0:responsibilityType>technical</ns0:responsibilityType>
                                <ns0:institutionType>non-profit</ns0:institutionType>
                <ns0:institutionURL>https://www.landcareresearch.co.nz/</ns0:institutionURL>
                                    <ns0:institutionIdentifier>ROR:02p9cyn66</ns0:institutionIdentifier>
                                <ns0:responsibilityStartDate />
                <ns0:responsibilityEndDate />
                                    <ns0:institutionContact>library@landcareresearch.co.nz</ns0:institutionContact>
                                    <ns0:institutionContact>mcglinchya@landcareresearch.co.nz</ns0:institutionContact>
                            </ns0:institution>
                            <ns0:policy>
                <ns0:policyName>BioHeritage Terms of Use</ns0:policyName>
                <ns0:policyURL>https://data.bioheritage.nz/terms_of_use</ns0:policyURL>
            </ns0:policy>
                    <ns0:policy>
                <ns0:policyName>Landcare Research New Zealand Terms of Use</ns0:policyName>
                <ns0:policyURL>https://datastore.landcareresearch.co.nz/terms_of_use</ns0:policyURL>
            </ns0:policy>
                <ns0:databaseAccess>
            <ns0:databaseAccessType>open</ns0:databaseAccessType>
                    </ns0:databaseAccess>
                    <ns0:databaseLicense>
                <ns0:databaseLicenseName>Copyrights</ns0:databaseLicenseName>
                <ns0:databaseLicenseURL>https://data.bioheritage.nz/terms_of_use</ns0:databaseLicenseURL>
            </ns0:databaseLicense>
                            <ns0:dataAccess>
                <ns0:dataAccessType>open</ns0:dataAccessType>
                            </ns0:dataAccess>
                            <ns0:dataLicense>
                <ns0:dataLicenseName>CC</ns0:dataLicenseName>
                <ns0:dataLicenseURL>https://creativecommons.org/licenses/</ns0:dataLicenseURL>
            </ns0:dataLicense>
                            <ns0:dataUpload>
                <ns0:dataUploadType>restricted</ns0:dataUploadType>
                                    <ns0:dataUploadRestriction>institutional membership</ns0:dataUploadRestriction>
                            </ns0:dataUpload>
                            <ns0:dataUploadLicense>
                <ns0:dataUploadLicenseName>Creative Commons licence</ns0:dataUploadLicenseName>
                <ns0:dataUploadLicenseURL>https://creativecommons.org/licenses/</ns0:dataUploadLicenseURL>
            </ns0:dataUploadLicense>
                            <ns0:software>
                <ns0:softwareName>CKAN</ns0:softwareName>
            </ns0:software>
                <ns0:versioning>yes</ns0:versioning>
                    <ns0:api apiType="REST">https://docs.ckan.org/en/2.7/api/</ns0:api>
                            <ns0:pidSystem>DOI</ns0:pidSystem>
                <ns0:citationGuidelineURL>https://data.bioheritage.nz/terms_of_use</ns0:citationGuidelineURL>
                <ns0:enhancedPublication>unknown</ns0:enhancedPublication>
        <ns0:qualityManagement>yes</ns0:qualityManagement>
                            <ns0:metadataStandard>
                <ns0:metadataStandardName metadataStandardScheme="DCC">DataCite Metadata Schema</ns0:metadataStandardName>
                <ns0:metadataStandardURL>http://www.dcc.ac.uk/resources/metadata-standards/datacite-metadata-schema</ns0:metadataStandardURL>
            </ns0:metadataStandard>
                        <ns0:remarks />
        <ns0:entryDate>2021-07-27</ns0:entryDate>
        <ns0:lastUpdate>2021-07-30</ns0:lastUpdate>
    </ns0:repository>
</ns0:re3data>